MANIFEST.in
README.rst
requirements.txt
setup.cfg
setup.py
fulmar/__init__.py
fulmar/base_spider.py
fulmar/cli.py
fulmar/log.py
fulmar/pprint.py
fulmar/utils.py
fulmar.egg-info/PKG-INFO
fulmar.egg-info/SOURCES.txt
fulmar.egg-info/dependency_links.txt
fulmar.egg-info/entry_points.txt
fulmar.egg-info/requires.txt
fulmar.egg-info/top_level.txt
fulmar/database/__init__.py
fulmar/database/mongodb.py
fulmar/message_queue/__init__.py
fulmar/message_queue/redis_queue.py
fulmar/projects/baidu_spider.py
fulmar/projects/nanshan_district.py
fulmar/projects/shenzhen.py
fulmar/projects/test_court.py
fulmar/scheduler/__init__.py
fulmar/scheduler/cron.py
fulmar/scheduler/projectdb.py
fulmar/scheduler/scheduler.py
fulmar/worker/__init__.py
fulmar/worker/http_utils.py
fulmar/worker/project_manager.py
fulmar/worker/requestor.py
fulmar/worker/response.py
fulmar/worker/result_handler.py
fulmar/worker/worker.py
tests/worker/test_requestor.py