Metadata-Version: 1.0
Name: fulmar
Version: 0.0.2
Summary: A Distributed Web Crawler System in Python
Home-page: https://github.com/tylderen/fulmar
Author: tylderen
Author-email: tylderen@gmail.com
License: UNKNOWN
Keywords: crawler,framework
Platform: UNKNOWN
